[{"brand":"GPX","model":"D200B","category":" Blu-Ray & DVD Players","source":"Office Depot","sourceType":"retailer","sourceId":4},{"brand":"LG","model":"BP350","category":" Blu-Ray & DVD Players","source":"Office Depot","sourceType":"retailer","sourceId":4},{"brand":"Technical Pro","model":"DV4000","category":" Blu-Ray & DVD Players","source":"Office Depot","sourceType":"retailer","sourceId":4},{"brand":"Samsung","model":"BD-J5700","category":" Blu-Ray & DVD Players","source":"Office Depot","sourceType":"retailer","sourceId":4},{"brand":"DPI","model":"DH300B","category":" Blu-Ray & DVD Players","source":"Office Depot","sourceType":"retailer","sourceId":4},{"brand":"LG","model":"BP255","category":" Blu-Ray & DVD Players","source":"Office Depot","sourceType":"retailer","sourceId":4},{"brand":"Samsung","model":"BD-J6300","category":" Blu-Ray & DVD Players","source":"Office Depot","sourceType":"retailer","sourceId":4},{"brand":"Samsung","model":"BD-J5100","category":" Blu-Ray & DVD Players","source":"Office Depot","sourceType":"retailer","sourceId":4},{"brand":"Panasonic","model":"DVD-S500","category":" Blu-Ray & DVD Players","source":"Office Depot","sourceType":"retailer","sourceId":4},{"brand":"LG","model":"DP132","category":" Blu-Ray & DVD Players","source":"Office Depot","sourceType":"retailer","sourceId":4}]